easygoogledocs/__init__.py
easy_google_docs-0.2.4.dist-info/METADATA
easy_google_docs-0.2.4.dist-info/WHEEL
easy_google_docs-0.2.4.dist-info/top_level.txt
easy_google_docs-0.2.4.dist-info/RECORD
